simplecalc_cmd/__init__.py
simplecalc_cmd/simplecalc_cmd.py
simpleCalc_cmd-1.2.2.dist-info/METADATA
simpleCalc_cmd-1.2.2.dist-info/WHEEL
simpleCalc_cmd-1.2.2.dist-info/entry_points.txt
simpleCalc_cmd-1.2.2.dist-info/top_level.txt
simpleCalc_cmd-1.2.2.dist-info/RECORD
