Metadata-Version: 2.1
Name: simpleCalc_cmd
Version: 1.2.2
Summary: Default template for PDM package
Author-email: sunwoo <summerham22@gmail.com>
License: MIT
Requires-Python: >=3.9
Requires-Dist: hc-add >=0.1.0
Requires-Dist: hc-mul >=0.1.0
Requires-Dist: hc-div >=0.1.0
